odoo/addons/account_payment_purchase/README.rst
odoo/addons/account_payment_purchase/__init__.py
odoo/addons/account_payment_purchase/__manifest__.py
odoo/addons/account_payment_purchase/i18n/account_payment_purchase.pot
odoo/addons/account_payment_purchase/i18n/ar.po
odoo/addons/account_payment_purchase/i18n/bg.po
odoo/addons/account_payment_purchase/i18n/bs.po
odoo/addons/account_payment_purchase/i18n/ca.po
odoo/addons/account_payment_purchase/i18n/cs.po
odoo/addons/account_payment_purchase/i18n/cs_CZ.po
odoo/addons/account_payment_purchase/i18n/de.po
odoo/addons/account_payment_purchase/i18n/el_GR.po
odoo/addons/account_payment_purchase/i18n/en_GB.po
odoo/addons/account_payment_purchase/i18n/es.po
odoo/addons/account_payment_purchase/i18n/es_AR.po
odoo/addons/account_payment_purchase/i18n/es_CR.po
odoo/addons/account_payment_purchase/i18n/es_EC.po
odoo/addons/account_payment_purchase/i18n/es_MX.po
odoo/addons/account_payment_purchase/i18n/es_PE.po
odoo/addons/account_payment_purchase/i18n/et.po
odoo/addons/account_payment_purchase/i18n/eu.po
odoo/addons/account_payment_purchase/i18n/fi.po
odoo/addons/account_payment_purchase/i18n/fr.po
odoo/addons/account_payment_purchase/i18n/fr_CA.po
odoo/addons/account_payment_purchase/i18n/fr_CH.po
odoo/addons/account_payment_purchase/i18n/fr_FR.po
odoo/addons/account_payment_purchase/i18n/gl.po
odoo/addons/account_payment_purchase/i18n/hr.po
odoo/addons/account_payment_purchase/i18n/hr_HR.po
odoo/addons/account_payment_purchase/i18n/hu.po
odoo/addons/account_payment_purchase/i18n/id.po
odoo/addons/account_payment_purchase/i18n/it.po
odoo/addons/account_payment_purchase/i18n/ja.po
odoo/addons/account_payment_purchase/i18n/lt.po
odoo/addons/account_payment_purchase/i18n/mk.po
odoo/addons/account_payment_purchase/i18n/mn.po
odoo/addons/account_payment_purchase/i18n/nb.po
odoo/addons/account_payment_purchase/i18n/nb_NO.po
odoo/addons/account_payment_purchase/i18n/nl.po
odoo/addons/account_payment_purchase/i18n/nl_BE.po
odoo_addon_account_payment_purchase-19.0.1.0.0.2.dist-info/METADATA
odoo_addon_account_payment_purchase-19.0.1.0.0.2.dist-info/WHEEL
odoo_addon_account_payment_purchase-19.0.1.0.0.2.dist-info/top_level.txt
odoo_addon_account_payment_purchase-19.0.1.0.0.2.dist-info/RECORD
