Metadata-Version: 2.1
Name: odoo-addon-account_payment_purchase
Version: 19.0.1.0.0.2
Requires-Dist: odoo-addon-account_payment_mode==19.0.*
Requires-Dist: odoo==19.0.*
Summary: Adds Bank Account and Payment Mode on Purchase Orders
Home-page: https://github.com/OCA/bank-payment
License: AGPL-3
Author: Akretion, Tecnativa, Odoo Community Association (OCA)
Author-email: support@odoo-community.org
Classifier: Programming Language :: Python
Classifier: Framework :: Odoo
Classifier: Framework :: Odoo :: 19.0
Classifier: License :: OSI Approved :: GNU Affero General Public License v3
